Metadata-Version: 1.1
Name: outproc
Version: 0.18
Summary: Pluggable Output Processor
Home-page: http://zaufi.github.io/pluggable-output-processor.html
Author: Alex Turbov
Author-email: I.zaufi@gmail.com
License: GNU General Public License v3 or later (GPLv3+)
Download-URL: https://github.com/zaufi/pluggable-output-processor/archive/version-0.18.tar.gz
Keywords: console gcc make cmake ouput colorizer
Platform: UNKNOWN
Classifier: Development Status :: 4 - Beta
Classifier: Environment :: Console
Classifier: Intended Audience :: Developers
Classifier: License :: OSI Approved :: GNU General Public License v3 or later (GPLv3+)
Classifier: Natural Language :: English
Classifier: Operating System :: POSIX :: Linux
Classifier: Programming Language :: Python :: 3.5
Classifier: Topic :: Utilities
